hfcam.py
fzj_hfcam-0.3.dist-info/METADATA
fzj_hfcam-0.3.dist-info/WHEEL
fzj_hfcam-0.3.dist-info/top_level.txt
fzj_hfcam-0.3.dist-info/RECORD
